docitup/__init__.py
docitup/base_loaders.py
docitup/docling_loaders.py
docitup/fitz_loaders.py
docitup/llamaparse_loaders.py
docitup/markitdown_loaders.py
docitup/pymupdf4llm_loaders.py
docitup/pypdf2_loaders.py
docitup/pypdf_loaders.py
docitup-0.1.4.dist-info/LICENSE
docitup-0.1.4.dist-info/METADATA
docitup-0.1.4.dist-info/WHEEL
docitup-0.1.4.dist-info/RECORD
