Metadata-Version: 2.3
Name: docitup
Version: 0.1.4
Summary: 
Author: Panindhra
Author-email: phanitallapudi@gmail.com
Requires-Python: >=3.12,<4.0
Classifier: Programming Language :: Python :: 3
Classifier: Programming Language :: Python :: 3.12
Classifier: Programming Language :: Python :: 3.13
Requires-Dist: docling (>=2.14.0,<3.0.0)
Requires-Dist: langchain (>=0.3.13,<0.4.0)
Requires-Dist: langchain-community (>=0.3.13,<0.4.0)
Requires-Dist: llama-index-readers-file (>=0.4.1,<0.5.0)
Requires-Dist: llama-parse (>=0.5.19,<0.6.0)
Requires-Dist: markitdown (>=0.0.1a3,<0.0.2)
Requires-Dist: pymupdf (>=1.25.1,<2.0.0)
Requires-Dist: pymupdf4llm (>=0.0.17,<0.0.18)
Requires-Dist: pypdf (>=5.1.0,<6.0.0)
Requires-Dist: pypdf2 (>=3.0.1,<4.0.0)
